pon-0.1.1.dist-info/namespace_packages.txt
pon-0.1.1.dist-info/WHEEL
pon-0.1.1.dist-info/top_level.txt
pon-0.1.1.dist-info/RECORD
pon-0.1.1.dist-info/metadata.json
pon-0.1.1.dist-info/METADATA
pon-0.1.1.dist-info/DESCRIPTION.rst
pon-0.1.1.dist-info/LICENSE.txt
pon/__init__.py
pon/dump.py
