Metadata-Version: 2.0
Name: pon
Version: 0.1.1
Summary: Python Object Notation
Home-page: https://bitbucket.org/ruamel/pon
Author: Anthon van der Neut
Author-email: a.van.der.neut@ruamel.eu
License: MIT license
Keywords: pon object-notation json yaml xml
Platform: UNKNOWN
Classifier: Development Status :: 4 - Beta
Classifier: Intended Audience :: Developers
Classifier: License :: OSI Approved :: MIT License
Classifier: Operating System :: OS Independent
Classifier: Programming Language :: Python
Requires-Dist: ruamel.ordereddict
